jntajis/_jntajis.cpython-39-x86_64-linux-gnu.so
jntajis/py.typed
jntajis/gen.py
jntajis/_jntajis.c
jntajis/_jntajis.pyx
jntajis/_jntajis.h
jntajis/_jntajis.pyi
jntajis/__init__.py
jntajis/tests/test_mj_translit.py
jntajis/tests/test_encoder.py
jntajis/xlsx_parser/parser.py
jntajis/xlsx_parser/xmlutils.py
jntajis/xlsx_parser/__init__.py
jntajis_python-0.0.13.dist-info/RECORD
jntajis_python-0.0.13.dist-info/METADATA
jntajis_python-0.0.13.dist-info/LICENSE
jntajis_python-0.0.13.dist-info/WHEEL
jntajis_python-0.0.13.dist-info/top_level.txt
