Metadata-Version: 2.1
Name: jntajis-python
Version: 0.0.13
Summary: A fast character conversion and transliteration library based on the scheme defined for Japan National Tax Agency's corporate number system.
Home-page: https://github.com/opencollector/jntajis-python
Author: Open Collector, inc.
Author-email: <info@opencollector.co.jp>
License: BSD License
Keywords: Unicode,JIS,encoding,conversion,transliteration,Japanese
Platform: UNKNOWN
Classifier: License :: OSI Approved :: BSD License
Classifier: Programming Language :: Python :: 3
Classifier: Programming Language :: Python :: 3.8
Classifier: Programming Language :: Python :: 3.9
Classifier: Topic :: Text Processing :: Filters
Requires-Python: >=3.8
Provides-Extra: dev
